[
  {
    "_id": "62bf2292c9adcd56eee32e4a",
    "time": "10:45",
    "firstName": "Mcintosh",
    "lastName": "Ross",
    "bookingReference": 44271852,
    "nhsNumber": 26489196,
    "special": "immunosupressed",
    "appointmentType": "Pfizer-BioNTech General Dose 1",
    "dateOfBirth": "1988-08-22T08:16:44"
  },
  {
    "_id": "62bf2292b721f23583381377",
    "time": "16:45",
    "firstName": "Cassandra",
    "lastName": "Barton",
    "bookingReference": 41933261,
    "nhsNumber": 73720443,
    "special": "no-additional-checks",
    "appointmentType": "Moderna Booster",
    "dateOfBirth": "1935-10-07T12:29:43"
  },
  {
    "_id": "62bf2292f7fbd8a4d460cdb0",
    "time": "11:05",
    "firstName": "Walls",
    "lastName": "Cline",
    "bookingReference": 57022504,
    "nhsNumber": 10299936,
    "special": "under-16-overseas",
    "appointmentType": "Moderna Booster",
    "dateOfBirth": "2020-05-19T09:41:22"
  },
  {
    "_id": "62bf229229ec288011e6388f",
    "time": "11:55",
    "firstName": "Wiley",
    "lastName": "Rodgers",
    "bookingReference": 54329126,
    "nhsNumber": 16838382,
    "special": "immunosupressed",
    "appointmentType": "Pfizer-BioNTech General Dose 1",
    "dateOfBirth": "1987-04-25T09:06:20"
  },
  {
    "_id": "62bf229243dcf804961aedcf",
    "time": "17:50",
    "firstName": "Montoya",
    "lastName": "Lopez",
    "bookingReference": 41014908,
    "nhsNumber": 34494261,
    "special": "hsc-worker",
    "appointmentType": "Comirnaty10 Dose 1",
    "dateOfBirth": "2015-09-02T09:06:55"
  },
  {
    "_id": "62bf22924f9f759d4b6c5f28",
    "time": "17:40",
    "firstName": "Evangelina",
    "lastName": "Emerson",
    "bookingReference": 91816686,
    "nhsNumber": 36883624,
    "special": "no-additional-checks",
    "appointmentType": "Overseas vaccination evidence check",
    "dateOfBirth": "2011-08-12T11:01:13"
  },
  {
    "_id": "62bf2292d874b2cd25305128",
    "time": "11:30",
    "firstName": "Elma",
    "lastName": "Watts",
    "bookingReference": 12614954,
    "nhsNumber": 72425671,
    "special": "under-16-overseas",
    "appointmentType": "Moderna Booster",
    "dateOfBirth": "1980-04-08T06:15:48"
  },
  {
    "_id": "62bf229205c8da524176fda0",
    "time": "13:25",
    "firstName": "Addie",
    "lastName": "Park",
    "bookingReference": 70177140,
    "nhsNumber": 99856493,
    "special": "under-16-overseas",
    "appointmentType": "Oxford-AstraZeneca Booster",
    "dateOfBirth": "1986-05-30T03:34:33"
  },
  {
    "_id": "62bf2292f060e53b368314de",
    "time": "13:20",
    "firstName": "House",
    "lastName": "Scott",
    "bookingReference": 99497227,
    "nhsNumber": 71811340,
    "special": "under-16-overseas",
    "appointmentType": "Moderna-Dose 1",
    "dateOfBirth": "1967-08-01T07:55:27"
  },
  {
    "_id": "62bf2292ffe44d74a96c989a",
    "time": "09:40",
    "firstName": "Patsy",
    "lastName": "Simon",
    "bookingReference": 82759832,
    "nhsNumber": 47752342,
    "special": "hsc-worker",
    "appointmentType": "Overseas vaccination evidence check",
    "dateOfBirth": "1996-02-06T09:35:09"
  },
  {
    "_id": "62bf229212a31002d4246b50",
    "time": "11:40",
    "firstName": "Nicole",
    "lastName": "Nicholson",
    "bookingReference": 98923195,
    "nhsNumber": 27895812,
    "special": "hsc-worker",
    "appointmentType": "Overseas vaccination evidence check",
    "dateOfBirth": "1951-02-19T11:29:57"
  },
  {
    "_id": "62bf2292468a466c47b3bd55",
    "time": "12:25",
    "firstName": "Sheri",
    "lastName": "Valentine",
    "bookingReference": 36568980,
    "nhsNumber": 65478076,
    "special": "hsc-worker",
    "appointmentType": "Overseas vaccination evidence check",
    "dateOfBirth": "1932-09-03T12:00:19"
  },
  {
    "_id": "62bf2292532faeba22249027",
    "time": "18:15",
    "firstName": "Lynn",
    "lastName": "Greene",
    "bookingReference": 14862134,
    "nhsNumber": 98677168,
    "special": "hsc-worker",
    "appointmentType": "Oxford-AstraZeneca General Dose 2",
    "dateOfBirth": "1943-09-09T10:41:45"
  },
  {
    "_id": "62bf229203de722b5b57f556",
    "time": "17:00",
    "firstName": "Pickett",
    "lastName": "Wilson",
    "bookingReference": 82850704,
    "nhsNumber": 62423422,
    "special": "no-additional-checks",
    "appointmentType": "Moderna-Dose 2",
    "dateOfBirth": "1970-10-17T06:22:45"
  },
  {
    "_id": "62bf2292263d41ed4cdc23aa",
    "time": "12:15",
    "firstName": "Karina",
    "lastName": "Norman",
    "bookingReference": 26954019,
    "nhsNumber": 89328206,
    "special": "under-16-overseas",
    "appointmentType": "Oxford-AstraZeneca General Dose 2",
    "dateOfBirth": "1934-03-10T04:17:26"
  },
  {
    "_id": "62bf2292856dd72903958b8c",
    "time": "12:10",
    "firstName": "Eloise",
    "lastName": "Webb",
    "bookingReference": 12910008,
    "nhsNumber": 73174065,
    "special": "under-16-overseas",
    "appointmentType": "Moderna Booster",
    "dateOfBirth": "1963-10-02T07:01:20"
  },
  {
    "_id": "62bf22920ed6ee77b74ba91c",
    "time": "12:00",
    "firstName": "Silvia",
    "lastName": "Clemons",
    "bookingReference": 63633244,
    "nhsNumber": 91145264,
    "special": "immunosupressed",
    "appointmentType": "Oxford-AstraZeneca General Dose 1",
    "dateOfBirth": "2019-05-23T04:24:50"
  },
  {
    "_id": "62bf2292b40ad1c3af26e746",
    "time": "09:35",
    "firstName": "Edna",
    "lastName": "Fischer",
    "bookingReference": 19363382,
    "nhsNumber": 83645524,
    "special": "no-additional-checks",
    "appointmentType": "Oxford-AstraZeneca General Dose 2",
    "dateOfBirth": "2003-02-03T12:21:58"
  },
  {
    "_id": "62bf2292759546d22306bd18",
    "time": "16:45",
    "firstName": "Potter",
    "lastName": "Ochoa",
    "bookingReference": 19827175,
    "nhsNumber": 99240780,
    "special": "immunosupressed",
    "appointmentType": "Moderna-Dose 1",
    "dateOfBirth": "2003-06-20T10:32:58"
  },
  {
    "_id": "62bf2292a7f28959a65688fe",
    "time": "11:55",
    "firstName": "Burks",
    "lastName": "Atkins",
    "bookingReference": 85720004,
    "nhsNumber": 69921400,
    "special": "hsc-worker",
    "appointmentType": "Comirnaty10 Dose 1",
    "dateOfBirth": "1932-09-10T11:13:09"
  },
  {
    "_id": "62bf2292f26f815212a29d97",
    "time": "13:45",
    "firstName": "Ashlee",
    "lastName": "Washington",
    "bookingReference": 60612949,
    "nhsNumber": 21296079,
    "special": "under-16-overseas",
    "appointmentType": "Moderna-Dose 2",
    "dateOfBirth": "2012-08-24T07:03:43"
  },
  {
    "_id": "62bf22928f7e391388b3df20",
    "time": "14:10",
    "firstName": "Hatfield",
    "lastName": "Stafford",
    "bookingReference": 72160136,
    "nhsNumber": 29667568,
    "special": "under-16-overseas",
    "appointmentType": "Pfizer-BioNTech General Dose 1",
    "dateOfBirth": "1983-09-30T03:29:56"
  },
  {
    "_id": "62bf2292b6b447a50e56d8c1",
    "time": "12:40",
    "firstName": "Lesley",
    "lastName": "Flynn",
    "bookingReference": 15713873,
    "nhsNumber": 55188912,
    "special": "hsc-worker",
    "appointmentType": "Moderna-Dose 1",
    "dateOfBirth": "1971-10-05T10:51:47"
  },
  {
    "_id": "62bf2292e1124af69825ac2e",
    "time": "12:05",
    "firstName": "Sawyer",
    "lastName": "Manning",
    "bookingReference": 67814493,
    "nhsNumber": 80371068,
    "special": "hsc-worker",
    "appointmentType": "Comirnaty10 Dose 1",
    "dateOfBirth": "1985-11-18T12:08:28"
  },
  {
    "_id": "62bf229268b6511875a1c3c9",
    "time": "15:25",
    "firstName": "Benjamin",
    "lastName": "Mccullough",
    "bookingReference": 54369468,
    "nhsNumber": 53258374,
    "special": "hsc-worker",
    "appointmentType": "Oxford-AstraZeneca Booster",
    "dateOfBirth": "1968-09-19T02:52:44"
  },
  {
    "_id": "62bf229290ec0fb30331a9e7",
    "time": "17:25",
    "firstName": "Kelley",
    "lastName": "Nielsen",
    "bookingReference": 31797877,
    "nhsNumber": 16964047,
    "special": "no-additional-checks",
    "appointmentType": "Oxford-AstraZeneca General Dose 1",
    "dateOfBirth": "1942-01-08T03:32:22"
  },
  {
    "_id": "62bf229282c41f3a762b76b7",
    "time": "16:10",
    "firstName": "Kerri",
    "lastName": "Juarez",
    "bookingReference": 20722899,
    "nhsNumber": 39939724,
    "special": "hsc-worker",
    "appointmentType": "Moderna-Dose 1",
    "dateOfBirth": "1951-05-28T03:11:44"
  },
  {
    "_id": "62bf22924dfd656f1aebd4f2",
    "time": "09:15",
    "firstName": "Richards",
    "lastName": "Page",
    "bookingReference": 89041735,
    "nhsNumber": 97442033,
    "special": "under-16-overseas",
    "appointmentType": "Moderna Booster",
    "dateOfBirth": "1945-05-15T02:01:42"
  },
  {
    "_id": "62bf22927be65ceae6ab1045",
    "time": "09:00",
    "firstName": "Beasley",
    "lastName": "Holloway",
    "bookingReference": 10130271,
    "nhsNumber": 22515419,
    "special": "under-16-overseas",
    "appointmentType": "Pfizer-BioNTech Booster",
    "dateOfBirth": "2019-06-01T12:15:11"
  },
  {
    "_id": "62bf2292d5b6593847e6dd5d",
    "time": "10:45",
    "firstName": "Adkins",
    "lastName": "Hunter",
    "bookingReference": 72405454,
    "nhsNumber": 64747643,
    "special": "hsc-worker",
    "appointmentType": "Moderna Booster",
    "dateOfBirth": "1939-09-12T12:41:16"
  },
  {
    "_id": "62bf2292f81f6ac3812ec464",
    "time": "11:35",
    "firstName": "Fox",
    "lastName": "Knowles",
    "bookingReference": 92098799,
    "nhsNumber": 96118075,
    "special": "under-16-overseas",
    "appointmentType": "Pfizer-BioNTech General Dose 2",
    "dateOfBirth": "1943-09-17T11:40:45"
  },
  {
    "_id": "62bf229283fc45e324cb291a",
    "time": "14:00",
    "firstName": "Nancy",
    "lastName": "Whitaker",
    "bookingReference": 78955543,
    "nhsNumber": 76616876,
    "special": "immunosupressed",
    "appointmentType": "Oxford-AstraZeneca General Dose 2",
    "dateOfBirth": "1974-08-10T07:44:31"
  },
  {
    "_id": "62bf2292a3a41358c397e4da",
    "time": "13:20",
    "firstName": "Leon",
    "lastName": "Hays",
    "bookingReference": 38856036,
    "nhsNumber": 39612461,
    "special": "immunosupressed",
    "appointmentType": "Oxford-AstraZeneca General Dose 1",
    "dateOfBirth": "1974-07-05T07:03:29"
  },
  {
    "_id": "62bf2292872714190cddfe31",
    "time": "09:05",
    "firstName": "Mcguire",
    "lastName": "Justice",
    "bookingReference": 16245955,
    "nhsNumber": 47801955,
    "special": "no-additional-checks",
    "appointmentType": "Pfizer-BioNTech Booster",
    "dateOfBirth": "1935-11-09T07:44:57"
  },
  {
    "_id": "62bf229284c53d26a051095c",
    "time": "13:25",
    "firstName": "Angelique",
    "lastName": "Carlson",
    "bookingReference": 27495900,
    "nhsNumber": 70197831,
    "special": "immunosupressed",
    "appointmentType": "Oxford-AstraZeneca General Dose 1",
    "dateOfBirth": "1934-08-13T07:55:53"
  },
  {
    "_id": "62bf2292b566f9b803fe5bb6",
    "time": "16:45",
    "firstName": "Bell",
    "lastName": "Huff",
    "bookingReference": 38218161,
    "nhsNumber": 49804518,
    "special": "hsc-worker",
    "appointmentType": "Moderna-Dose 2",
    "dateOfBirth": "1963-06-19T10:39:53"
  },
  {
    "_id": "62bf22926b97cfecbdd22785",
    "time": "11:40",
    "firstName": "Valarie",
    "lastName": "Hamilton",
    "bookingReference": 61473203,
    "nhsNumber": 99198627,
    "special": "no-additional-checks",
    "appointmentType": "Moderna Booster",
    "dateOfBirth": "1947-07-31T07:56:20"
  },
  {
    "_id": "62bf22923464905736ff90c5",
    "time": "13:45",
    "firstName": "Olsen",
    "lastName": "Wolfe",
    "bookingReference": 88969059,
    "nhsNumber": 85382947,
    "special": "immunosupressed",
    "appointmentType": "Pfizer-BioNTech General Dose 1",
    "dateOfBirth": "1955-04-03T02:43:35"
  },
  {
    "_id": "62bf22926752e39dd6123372",
    "time": "09:05",
    "firstName": "Workman",
    "lastName": "Harrison",
    "bookingReference": 11197985,
    "nhsNumber": 23867710,
    "special": "under-16-overseas",
    "appointmentType": "Comirnaty10 Dose 1",
    "dateOfBirth": "1934-10-31T11:21:46"
  },
  {
    "_id": "62bf2292ffdcd8d0c973cf91",
    "time": "09:45",
    "firstName": "Steele",
    "lastName": "Mcclure",
    "bookingReference": 40245477,
    "nhsNumber": 50765210,
    "special": "under-16-overseas",
    "appointmentType": "Pfizer-BioNTech General Dose 2",
    "dateOfBirth": "2017-09-03T02:11:30"
  },
  {
    "_id": "62bf229241cc9752e2517021",
    "time": "09:00",
    "firstName": "Heath",
    "lastName": "Petty",
    "bookingReference": 43563293,
    "nhsNumber": 67310314,
    "special": "immunosupressed",
    "appointmentType": "Overseas vaccination evidence check",
    "dateOfBirth": "2018-11-15T05:37:53"
  },
  {
    "_id": "62bf229209e17ffd7b5824eb",
    "time": "11:50",
    "firstName": "Sargent",
    "lastName": "Barker",
    "bookingReference": 35455646,
    "nhsNumber": 60318316,
    "special": "no-additional-checks",
    "appointmentType": "Oxford-AstraZeneca General Dose 1",
    "dateOfBirth": "2016-12-28T11:41:39"
  },
  {
    "_id": "62bf2292dabcda843872084b",
    "time": "10:00",
    "firstName": "Avery",
    "lastName": "Valdez",
    "bookingReference": 82772271,
    "nhsNumber": 87307400,
    "special": "under-16-overseas",
    "appointmentType": "Oxford-AstraZeneca Booster",
    "dateOfBirth": "1939-06-04T11:54:52"
  },
  {
    "_id": "62bf229276ab7aa1f4adc9d4",
    "time": "10:40",
    "firstName": "Luisa",
    "lastName": "Benjamin",
    "bookingReference": 55891412,
    "nhsNumber": 80161804,
    "special": "no-additional-checks",
    "appointmentType": "Comirnaty10 Dose 2",
    "dateOfBirth": "1981-02-05T03:11:05"
  },
  {
    "_id": "62bf229256fc2813304bdb71",
    "time": "17:45",
    "firstName": "Kramer",
    "lastName": "Aguilar",
    "bookingReference": 49614905,
    "nhsNumber": 67581079,
    "special": "hsc-worker",
    "appointmentType": "Pfizer-BioNTech General Dose 1",
    "dateOfBirth": "1937-01-03T02:24:19"
  },
  {
    "_id": "62bf22926e1c44b406f9291d",
    "time": "15:05",
    "firstName": "Kerr",
    "lastName": "Lynn",
    "bookingReference": 71546643,
    "nhsNumber": 28126488,
    "special": "under-16-overseas",
    "appointmentType": "Comirnaty10 Dose 2",
    "dateOfBirth": "1961-03-27T08:34:58"
  },
  {
    "_id": "62bf229266785fa9b72339cc",
    "time": "09:30",
    "firstName": "Ramsey",
    "lastName": "Diaz",
    "bookingReference": 83980513,
    "nhsNumber": 94746685,
    "special": "immunosupressed",
    "appointmentType": "Moderna-Dose 1",
    "dateOfBirth": "1976-11-24T11:09:54"
  },
  {
    "_id": "62bf22928c0205fdd14cfc65",
    "time": "18:30",
    "firstName": "Julie",
    "lastName": "Glass",
    "bookingReference": 58587849,
    "nhsNumber": 91612816,
    "special": "under-16-overseas",
    "appointmentType": "Oxford-AstraZeneca Booster",
    "dateOfBirth": "1978-03-25T08:40:41"
  },
  {
    "_id": "62bf2292a45bce2b2b605151",
    "time": "15:10",
    "firstName": "Helena",
    "lastName": "Snow",
    "bookingReference": 87579397,
    "nhsNumber": 18702610,
    "special": "under-16-overseas",
    "appointmentType": "Oxford-AstraZeneca Booster",
    "dateOfBirth": "1946-02-08T03:24:07"
  },
  {
    "_id": "62bf229230389e36e3462f4c",
    "time": "10:50",
    "firstName": "Maldonado",
    "lastName": "Ortega",
    "bookingReference": 40886599,
    "nhsNumber": 24229658,
    "special": "under-16-overseas",
    "appointmentType": "Moderna-Dose 2",
    "dateOfBirth": "2019-01-22T05:55:34"
  },
  {
    "_id": "62bf22925df2e7f63425811b",
    "time": "12:00",
    "firstName": "Vang",
    "lastName": "Moody",
    "bookingReference": 44184056,
    "nhsNumber": 17597197,
    "special": "immunosupressed",
    "appointmentType": "Pfizer-BioNTech Booster",
    "dateOfBirth": "1955-06-23T12:41:04"
  },
  {
    "_id": "62bf22927381ad5980fedd4d",
    "time": "12:45",
    "firstName": "Jennie",
    "lastName": "Walters",
    "bookingReference": 36741743,
    "nhsNumber": 53199328,
    "special": "no-additional-checks",
    "appointmentType": "Moderna-Dose 1",
    "dateOfBirth": "1994-02-16T04:51:31"
  },
  {
    "_id": "62bf22926b547f3e46a4cbef",
    "time": "11:25",
    "firstName": "Castillo",
    "lastName": "Lester",
    "bookingReference": 36262765,
    "nhsNumber": 50698063,
    "special": "hsc-worker",
    "appointmentType": "Pfizer-BioNTech General Dose 2",
    "dateOfBirth": "1994-03-16T10:14:20"
  },
  {
    "_id": "62bf22923e5d698fcc487642",
    "time": "10:35",
    "firstName": "Grace",
    "lastName": "Casey",
    "bookingReference": 89901154,
    "nhsNumber": 17935627,
    "special": "under-16-overseas",
    "appointmentType": "Moderna-Dose 2",
    "dateOfBirth": "1965-03-28T11:49:34"
  },
  {
    "_id": "62bf2292d8a997551c936987",
    "time": "18:35",
    "firstName": "Foreman",
    "lastName": "Salinas",
    "bookingReference": 38205770,
    "nhsNumber": 38245981,
    "special": "under-16-overseas",
    "appointmentType": "Oxford-AstraZeneca General Dose 2",
    "dateOfBirth": "1966-04-07T06:24:43"
  },
  {
    "_id": "62bf22922f3d85dd13de252d",
    "time": "11:05",
    "firstName": "Richard",
    "lastName": "Chambers",
    "bookingReference": 12168794,
    "nhsNumber": 24709010,
    "special": "immunosupressed",
    "appointmentType": "Moderna-Dose 1",
    "dateOfBirth": "1939-01-20T12:33:06"
  },
  {
    "_id": "62bf22925044871e069348a6",
    "time": "12:55",
    "firstName": "Verna",
    "lastName": "Ramirez",
    "bookingReference": 27086988,
    "nhsNumber": 10444069,
    "special": "no-additional-checks",
    "appointmentType": "Pfizer-BioNTech Booster",
    "dateOfBirth": "1992-03-11T05:31:16"
  },
  {
    "_id": "62bf2292e6bc7c8c88623bd9",
    "time": "17:15",
    "firstName": "Marilyn",
    "lastName": "Russo",
    "bookingReference": 81200231,
    "nhsNumber": 53804302,
    "special": "no-additional-checks",
    "appointmentType": "Oxford-AstraZeneca General Dose 2",
    "dateOfBirth": "2008-08-30T05:09:34"
  },
  {
    "_id": "62bf2292bcf26cfc83f6fc20",
    "time": "11:55",
    "firstName": "Cohen",
    "lastName": "Ware",
    "bookingReference": 97789384,
    "nhsNumber": 65336445,
    "special": "under-16-overseas",
    "appointmentType": "Pfizer-BioNTech General Dose 1",
    "dateOfBirth": "1986-05-20T12:59:54"
  },
  {
    "_id": "62bf22926713e27c16031e6a",
    "time": "18:05",
    "firstName": "Britt",
    "lastName": "Poole",
    "bookingReference": 95656977,
    "nhsNumber": 20248654,
    "special": "no-additional-checks",
    "appointmentType": "Oxford-AstraZeneca General Dose 2",
    "dateOfBirth": "1976-02-05T07:45:38"
  },
  {
    "_id": "62bf22920b70caa70acbe626",
    "time": "15:45",
    "firstName": "Kirby",
    "lastName": "King",
    "bookingReference": 44951107,
    "nhsNumber": 87389641,
    "special": "hsc-worker",
    "appointmentType": "Moderna-Dose 2",
    "dateOfBirth": "1936-02-06T04:02:27"
  },
  {
    "_id": "62bf2292f7d2567d3b28c670",
    "time": "17:30",
    "firstName": "Griffith",
    "lastName": "Wong",
    "bookingReference": 89378859,
    "nhsNumber": 72409962,
    "special": "under-16-overseas",
    "appointmentType": "Oxford-AstraZeneca General Dose 1",
    "dateOfBirth": "1973-04-22T09:38:57"
  },
  {
    "_id": "62bf22928de53765de64d5cc",
    "time": "15:40",
    "firstName": "Whitney",
    "lastName": "Gonzales",
    "bookingReference": 97165973,
    "nhsNumber": 98202642,
    "special": "under-16-overseas",
    "appointmentType": "Moderna Booster",
    "dateOfBirth": "2019-03-29T08:29:38"
  },
  {
    "_id": "62bf2292a92c8903c1be6606",
    "time": "16:45",
    "firstName": "Gibson",
    "lastName": "Dunlap",
    "bookingReference": 98119481,
    "nhsNumber": 76116003,
    "special": "hsc-worker",
    "appointmentType": "Pfizer-BioNTech General Dose 2",
    "dateOfBirth": "1934-03-22T02:09:07"
  },
  {
    "_id": "62bf229282c19874e48d5c0c",
    "time": "15:15",
    "firstName": "Madelyn",
    "lastName": "Merritt",
    "bookingReference": 25287735,
    "nhsNumber": 12328939,
    "special": "immunosupressed",
    "appointmentType": "Oxford-AstraZeneca General Dose 1",
    "dateOfBirth": "1945-05-11T12:42:31"
  },
  {
    "_id": "62bf2292f485a5fbfe74929c",
    "time": "12:05",
    "firstName": "Perez",
    "lastName": "Knox",
    "bookingReference": 51805113,
    "nhsNumber": 39187625,
    "special": "hsc-worker",
    "appointmentType": "Moderna-Dose 2",
    "dateOfBirth": "1980-04-25T02:22:24"
  },
  {
    "_id": "62bf2292e518b3a4dd635f52",
    "time": "16:45",
    "firstName": "Mckenzie",
    "lastName": "Mcfadden",
    "bookingReference": 92949818,
    "nhsNumber": 24619873,
    "special": "immunosupressed",
    "appointmentType": "Moderna Booster",
    "dateOfBirth": "1975-08-08T06:32:19"
  },
  {
    "_id": "62bf229240cf8731e14e11bc",
    "time": "16:55",
    "firstName": "Mcgee",
    "lastName": "Workman",
    "bookingReference": 72259470,
    "nhsNumber": 73253902,
    "special": "under-16-overseas",
    "appointmentType": "Oxford-AstraZeneca General Dose 1",
    "dateOfBirth": "2021-10-15T10:01:11"
  },
  {
    "_id": "62bf2292eda84e6ef719dc0a",
    "time": "16:50",
    "firstName": "Porter",
    "lastName": "Barry",
    "bookingReference": 69011090,
    "nhsNumber": 46179013,
    "special": "no-additional-checks",
    "appointmentType": "Moderna Booster",
    "dateOfBirth": "1988-09-20T07:35:48"
  },
  {
    "_id": "62bf22923b6b37706778c6f5",
    "time": "09:05",
    "firstName": "Billie",
    "lastName": "Nichols",
    "bookingReference": 47463928,
    "nhsNumber": 87636242,
    "special": "under-16-overseas",
    "appointmentType": "Oxford-AstraZeneca General Dose 1",
    "dateOfBirth": "1952-11-05T02:20:59"
  },
  {
    "_id": "62bf229270ab09183721b862",
    "time": "14:10",
    "firstName": "Nichols",
    "lastName": "Durham",
    "bookingReference": 57062797,
    "nhsNumber": 92135880,
    "special": "no-additional-checks",
    "appointmentType": "Oxford-AstraZeneca Booster",
    "dateOfBirth": "1948-10-20T02:34:06"
  },
  {
    "_id": "62bf2292ccc59b633d66513b",
    "time": "16:30",
    "firstName": "Keri",
    "lastName": "Hoover",
    "bookingReference": 66091265,
    "nhsNumber": 55316247,
    "special": "hsc-worker",
    "appointmentType": "Comirnaty10 Dose 1",
    "dateOfBirth": "1977-09-07T01:44:14"
  },
  {
    "_id": "62bf2292b41ea232425e5c58",
    "time": "09:05",
    "firstName": "Watkins",
    "lastName": "Guthrie",
    "bookingReference": 30361540,
    "nhsNumber": 65033780,
    "special": "under-16-overseas",
    "appointmentType": "Oxford-AstraZeneca General Dose 2",
    "dateOfBirth": "1999-06-12T12:53:17"
  },
  {
    "_id": "62bf22927e4b28b6dff6d69a",
    "time": "10:15",
    "firstName": "Nanette",
    "lastName": "Armstrong",
    "bookingReference": 77652444,
    "nhsNumber": 90060622,
    "special": "under-16-overseas",
    "appointmentType": "Oxford-AstraZeneca General Dose 2",
    "dateOfBirth": "1981-06-11T10:58:53"
  },
  {
    "_id": "62bf22927a6f7615c4a09f24",
    "time": "18:45",
    "firstName": "Ford",
    "lastName": "Weaver",
    "bookingReference": 50163949,
    "nhsNumber": 65439767,
    "special": "immunosupressed",
    "appointmentType": "Comirnaty10 Dose 1",
    "dateOfBirth": "2003-05-05T04:06:20"
  },
  {
    "_id": "62bf229250cbaad133e24809",
    "time": "14:05",
    "firstName": "Rita",
    "lastName": "Miles",
    "bookingReference": 76363098,
    "nhsNumber": 45179955,
    "special": "immunosupressed",
    "appointmentType": "Oxford-AstraZeneca General Dose 1",
    "dateOfBirth": "1941-11-16T01:38:14"
  },
  {
    "_id": "62bf229244397cb0197657a8",
    "time": "16:50",
    "firstName": "Leola",
    "lastName": "Henry",
    "bookingReference": 79353472,
    "nhsNumber": 14825063,
    "special": "no-additional-checks",
    "appointmentType": "Oxford-AstraZeneca General Dose 1",
    "dateOfBirth": "1952-01-17T05:57:22"
  },
  {
    "_id": "62bf22925af8a7e49c19a278",
    "time": "16:25",
    "firstName": "Avis",
    "lastName": "Bowen",
    "bookingReference": 33544258,
    "nhsNumber": 92522453,
    "special": "immunosupressed",
    "appointmentType": "Overseas vaccination evidence check",
    "dateOfBirth": "1975-02-28T08:24:24"
  },
  {
    "_id": "62bf2292d10db0e1b3c05828",
    "time": "15:40",
    "firstName": "Pearlie",
    "lastName": "Frank",
    "bookingReference": 83614606,
    "nhsNumber": 95651212,
    "special": "immunosupressed",
    "appointmentType": "Pfizer-BioNTech General Dose 1",
    "dateOfBirth": "2001-07-31T08:55:14"
  },
  {
    "_id": "62bf22926dc1638e13cbba24",
    "time": "16:25",
    "firstName": "Brittany",
    "lastName": "Berry",
    "bookingReference": 77659290,
    "nhsNumber": 37027810,
    "special": "under-16-overseas",
    "appointmentType": "Oxford-AstraZeneca General Dose 1",
    "dateOfBirth": "1990-02-21T03:00:46"
  },
  {
    "_id": "62bf2292f9acc116761b4401",
    "time": "12:20",
    "firstName": "Ernestine",
    "lastName": "Church",
    "bookingReference": 35841619,
    "nhsNumber": 87266113,
    "special": "no-additional-checks",
    "appointmentType": "Comirnaty10 Dose 2",
    "dateOfBirth": "2011-06-21T09:36:44"
  },
  {
    "_id": "62bf22920a718d1dea3a0c93",
    "time": "18:20",
    "firstName": "Patricia",
    "lastName": "Sanford",
    "bookingReference": 15645077,
    "nhsNumber": 99160241,
    "special": "immunosupressed",
    "appointmentType": "Oxford-AstraZeneca Booster",
    "dateOfBirth": "1974-02-04T05:09:48"
  },
  {
    "_id": "62bf22920f71951e2b958b9f",
    "time": "09:05",
    "firstName": "Poole",
    "lastName": "Reed",
    "bookingReference": 18712280,
    "nhsNumber": 77636908,
    "special": "no-additional-checks",
    "appointmentType": "Oxford-AstraZeneca General Dose 1",
    "dateOfBirth": "1995-12-22T11:11:31"
  },
  {
    "_id": "62bf2292797f5160f63844fe",
    "time": "09:00",
    "firstName": "Wolfe",
    "lastName": "Fleming",
    "bookingReference": 10913396,
    "nhsNumber": 55446863,
    "special": "immunosupressed",
    "appointmentType": "Overseas vaccination evidence check",
    "dateOfBirth": "1968-07-17T06:20:18"
  },
  {
    "_id": "62bf22926a1aa0a8b03557ed",
    "time": "16:40",
    "firstName": "Suzette",
    "lastName": "Booker",
    "bookingReference": 91359501,
    "nhsNumber": 17830158,
    "special": "hsc-worker",
    "appointmentType": "Comirnaty10 Dose 2",
    "dateOfBirth": "1988-07-13T11:19:02"
  },
  {
    "_id": "62bf229200eeebbc5edde193",
    "time": "17:10",
    "firstName": "Alisha",
    "lastName": "Moreno",
    "bookingReference": 73449489,
    "nhsNumber": 67905219,
    "special": "hsc-worker",
    "appointmentType": "Pfizer-BioNTech General Dose 1",
    "dateOfBirth": "1967-06-16T12:14:58"
  },
  {
    "_id": "62bf229267fb5a5d8227c4ed",
    "time": "11:25",
    "firstName": "Gillespie",
    "lastName": "Hayes",
    "bookingReference": 32503676,
    "nhsNumber": 32731223,
    "special": "hsc-worker",
    "appointmentType": "Pfizer-BioNTech General Dose 2",
    "dateOfBirth": "2006-07-22T02:53:57"
  },
  {
    "_id": "62bf2292837bd69cee2869b9",
    "time": "11:35",
    "firstName": "Ray",
    "lastName": "Hester",
    "bookingReference": 91553598,
    "nhsNumber": 53989817,
    "special": "under-16-overseas",
    "appointmentType": "Pfizer-BioNTech General Dose 2",
    "dateOfBirth": "1978-08-12T03:30:53"
  },
  {
    "_id": "62bf2292c666755874c177fe",
    "time": "16:20",
    "firstName": "Frederick",
    "lastName": "Warren",
    "bookingReference": 23121212,
    "nhsNumber": 55072184,
    "special": "immunosupressed",
    "appointmentType": "Oxford-AstraZeneca General Dose 1",
    "dateOfBirth": "1970-12-20T05:34:15"
  },
  {
    "_id": "62bf22924f53640bf60f4adc",
    "time": "12:00",
    "firstName": "Neal",
    "lastName": "Cash",
    "bookingReference": 17025192,
    "nhsNumber": 70319903,
    "special": "no-additional-checks",
    "appointmentType": "Pfizer-BioNTech General Dose 1",
    "dateOfBirth": "1987-07-01T06:57:21"
  },
  {
    "_id": "62bf2292894b1c84cb8bdd90",
    "time": "10:10",
    "firstName": "Samantha",
    "lastName": "Duran",
    "bookingReference": 34418816,
    "nhsNumber": 41319069,
    "special": "immunosupressed",
    "appointmentType": "Overseas vaccination evidence check",
    "dateOfBirth": "2002-05-29T03:27:49"
  },
  {
    "_id": "62bf22926f5e1bc47e3a0be1",
    "time": "16:20",
    "firstName": "Lakisha",
    "lastName": "Mendez",
    "bookingReference": 27173757,
    "nhsNumber": 59178652,
    "special": "immunosupressed",
    "appointmentType": "Oxford-AstraZeneca General Dose 1",
    "dateOfBirth": "1948-11-15T03:39:08"
  },
  {
    "_id": "62bf229285ff6c6c8807262b",
    "time": "17:45",
    "firstName": "Dale",
    "lastName": "Guerrero",
    "bookingReference": 18163289,
    "nhsNumber": 74485245,
    "special": "under-16-overseas",
    "appointmentType": "Moderna-Dose 1",
    "dateOfBirth": "1951-07-11T12:20:48"
  },
  {
    "_id": "62bf2292f7d64f0a25c43210",
    "time": "13:50",
    "firstName": "Knowles",
    "lastName": "Gay",
    "bookingReference": 59080739,
    "nhsNumber": 76634089,
    "special": "immunosupressed",
    "appointmentType": "Moderna Booster",
    "dateOfBirth": "1946-09-13T07:15:08"
  },
  {
    "_id": "62bf2292df3cf65f70f0dcbb",
    "time": "13:30",
    "firstName": "Faulkner",
    "lastName": "Albert",
    "bookingReference": 70766470,
    "nhsNumber": 32414129,
    "special": "no-additional-checks",
    "appointmentType": "Overseas vaccination evidence check",
    "dateOfBirth": "1933-08-27T09:12:38"
  },
  {
    "_id": "62bf2292cdb2e4ddae62fa48",
    "time": "09:55",
    "firstName": "Lana",
    "lastName": "Savage",
    "bookingReference": 51093249,
    "nhsNumber": 10918283,
    "special": "no-additional-checks",
    "appointmentType": "Pfizer-BioNTech General Dose 1",
    "dateOfBirth": "1938-07-31T07:28:17"
  },
  {
    "_id": "62bf229203a15cf6f024b4a6",
    "time": "09:50",
    "firstName": "Clarice",
    "lastName": "Cabrera",
    "bookingReference": 10086761,
    "nhsNumber": 93024881,
    "special": "no-additional-checks",
    "appointmentType": "Comirnaty10 Dose 1",
    "dateOfBirth": "1939-08-24T06:42:41"
  },
  {
    "_id": "62bf2292fd9e12111f19d288",
    "time": "16:10",
    "firstName": "Gardner",
    "lastName": "Perry",
    "bookingReference": 90503051,
    "nhsNumber": 59697031,
    "special": "under-16-overseas",
    "appointmentType": "Comirnaty10 Dose 1",
    "dateOfBirth": "2017-01-23T05:08:19"
  },
  {
    "_id": "62bf2292608967db2d1d883b",
    "time": "12:15",
    "firstName": "Nash",
    "lastName": "Padilla",
    "bookingReference": 82515437,
    "nhsNumber": 15436053,
    "special": "immunosupressed",
    "appointmentType": "Oxford-AstraZeneca Booster",
    "dateOfBirth": "1930-04-23T03:54:59"
  },
  {
    "_id": "62bf22925c6e93089893814c",
    "time": "12:10",
    "firstName": "Mack",
    "lastName": "Slater",
    "bookingReference": 41672584,
    "nhsNumber": 87090810,
    "special": "under-16-overseas",
    "appointmentType": "Pfizer-BioNTech General Dose 2",
    "dateOfBirth": "1997-08-25T08:30:18"
  }
]
